tests/__init__.py
tests/test_client.py
mem_client-0.0.2.dist-info/LICENSE
mem_client-0.0.2.dist-info/METADATA
mem_client-0.0.2.dist-info/WHEEL
mem_client-0.0.2.dist-info/entry_points.txt
mem_client-0.0.2.dist-info/top_level.txt
mem_client-0.0.2.dist-info/RECORD
