Metadata-Version: 2.1
Name: mem-client
Version: 0.0.2
Summary: A brief description of your package
Home-page: https://github.com/ElviiAi/mem-client
Author: Jaro Uljanovs
Author-email: jaro@aiforall.dev
Classifier: Programming Language :: Python :: 3
Classifier: License :: OSI Approved :: MIT License
Classifier: Operating System :: OS Independent
Requires-Python: >=3.6
License-File: LICENSE
Requires-Dist: requests >=2.25.1
Requires-Dist: python-dotenv >=0.19.2
Requires-Dist: click >=8.0.3
